snxconnect.py
snxvpnversion.py
snxvpn_fix-1.5.1.data/scripts/snxconnect
snxvpn_fix-1.5.1.dist-info/LICENSE.TXT
snxvpn_fix-1.5.1.dist-info/METADATA
snxvpn_fix-1.5.1.dist-info/WHEEL
snxvpn_fix-1.5.1.dist-info/top_level.txt
snxvpn_fix-1.5.1.dist-info/RECORD
