Metadata-Version: 2.1
Name: snxvpn-fix
Version: 1.5.1
Summary: Command-line utility to connect to a Checkpoint SSL VPN 
Home-page: https://github.com/dimastbk/snxvpn
License: BSD License
Platform: Linux
Classifier: Development Status :: 3 - Alpha
Classifier: License :: OSI Approved :: BSD License
Classifier: Operating System :: POSIX :: Linux
Classifier: Programming Language :: Python
Classifier: Intended Audience :: Developers
Classifier: Intended Audience :: Science/Research
Classifier: Intended Audience :: Information Technology
Classifier: Intended Audience :: System Administrators
Classifier: Programming Language :: Python :: 2.7
Classifier: Programming Language :: Python :: 3.4
Classifier: Programming Language :: Python :: 3.5
Classifier: Programming Language :: Python :: 3.6
License-File: LICENSE.TXT
Requires-Dist: bs4
Requires-Dist: pycrypto
Requires-Dist: lxml
Requires-Dist: rsa
